install.json
package.json
env/share/jupyter/lab/static/package.json
env/share/jupyter/labextensions/jupyterlab_pygments/install.json
env/share/jupyter/labextensions/jupyterlab_pygments/package.json
env/share/jupyter/labextensions/lseg-analytics-jupyterlab/install.json
jupyter_config/server_config/lseg_analytics_jupyterlab.json
lseg_analytics_jupyterlab/__init__.py
lseg_analytics_jupyterlab/_version.py
lseg_analytics_jupyterlab/main.py
lseg_analytics_jupyterlab/labextension/package.json
lseg_analytics_jupyterlab/labextension/schemas/lseg-analytics-jupyterlab/package.json.orig
lseg_analytics_jupyterlab/labextension/schemas/lseg-analytics-jupyterlab/plugin.json
lseg_analytics_jupyterlab/labextension/static/262.49f9ad1514b4a9a3c778.js
lseg_analytics_jupyterlab/labextension/static/28acd39ce37d409c3ad9.jpg
lseg_analytics_jupyterlab/labextension/static/320.87036a66444e22e72d9b.js
lseg_analytics_jupyterlab/labextension/static/352.45165deb79c41298a0fa.js
lseg_analytics_jupyterlab/labextension/static/352.45165deb79c41298a0fa.js.LICENSE.txt
lseg_analytics_jupyterlab/labextension/static/540.406fff4bf87eb3af218f.js
lseg_analytics_jupyterlab/labextension/static/540.406fff4bf87eb3af218f.js.LICENSE.txt
lseg_analytics_jupyterlab/labextension/static/542.96a7b0802466f0318167.js
lseg_analytics_jupyterlab/labextension/static/552.ec1b24f07ab9b3266888.js
lseg_analytics_jupyterlab/labextension/static/685.9608a9026f055f4da320.js
lseg_analytics_jupyterlab/labextension/static/685.9608a9026f055f4da320.js.LICENSE.txt
lseg_analytics_jupyterlab/labextension/static/70.51549c136c1ec6ac3736.js
lseg_analytics_jupyterlab/labextension/static/877.60e1f68ecf1c95920eac.js
lseg_analytics_jupyterlab/labextension/static/877.60e1f68ecf1c95920eac.js.LICENSE.txt
lseg_analytics_jupyterlab/labextension/static/937.2d5f401f79792f425647.js
lseg_analytics_jupyterlab/labextension/static/937.2d5f401f79792f425647.js.LICENSE.txt
lseg_analytics_jupyterlab/labextension/static/cb1601a3c615d6c37e6d.png
lseg_analytics_jupyterlab-1.1.0.dist-info/METADATA
lseg_analytics_jupyterlab-1.1.0.dist-info/WHEEL
lseg_analytics_jupyterlab-1.1.0.dist-info/licenses/LICENSE.txt
lseg_analytics_jupyterlab-1.1.0.dist-info/RECORD
