Metadata-Version: 2.4
Name: lseg-analytics-jupyterlab
Version: 1.1.0
Dynamic: Keywords
Dynamic: Project-URL
Summary: Provides coding assistance for the LSEG Analytics Pricing Python SDK.
Author: LSEG.Publishers
License-Expression: LicenseRef-LSEG-Proprietary
License-File: LICENSE.txt
Classifier: Framework :: Jupyter
Classifier: Framework :: Jupyter :: JupyterLab
Classifier: Framework :: Jupyter :: JupyterLab :: 4
Classifier: Framework :: Jupyter :: JupyterLab :: Extensions
Classifier: Framework :: Jupyter :: JupyterLab :: Extensions :: Prebuilt
Classifier: Programming Language :: Python
Classifier: Programming Language :: Python :: 3
Classifier: Programming Language :: Python :: 3.8
Classifier: Programming Language :: Python :: 3.9
Classifier: Programming Language :: Python :: 3.10
Classifier: Programming Language :: Python :: 3.11
Classifier: Programming Language :: Python :: 3.12
Requires-Python: >=3.8
Requires-Dist: black
Requires-Dist: build
Requires-Dist: cryptography
Requires-Dist: datetime
Requires-Dist: debugpy
Requires-Dist: jupyterlab<5,>=4.1.4
Requires-Dist: pkce
Requires-Dist: pyjwt
Requires-Dist: pytest
Requires-Dist: pytest-cov
Requires-Dist: pytest-jupyter
Requires-Dist: pytest-mock
Requires-Dist: python-dotenv
Requires-Dist: requests
Requires-Dist: tornado
Requires-Dist: watchdog>=3.0.0
